MANIFEST.in
README.md
setup.py
Flask_ReactJS.egg-info/PKG-INFO
Flask_ReactJS.egg-info/SOURCES.txt
Flask_ReactJS.egg-info/dependency_links.txt
Flask_ReactJS.egg-info/requires.txt
Flask_ReactJS.egg-info/top_level.txt
flask_react/__init__.py
flask_react/babel.py
flask_react/core.py
flask_react/static/react/favicon.ico
flask_react/static/react/logo192.png
flask_react/static/react/logo512.png
flask_react/static/react/manifest.json
flask_react/static/react/js/App.js
flask_react/static/react/js/components.js
flask_react/static/react/js/index.js
flask_react/static/react/js/serviceWorker.js
flask_react/static/react/vendor/bootstrap.min.css
flask_react/static/react/vendor/bootstrap.min.css.map
flask_react/static/react/vendor/material-ui.deveolpment.js
flask_react/static/react/vendor/material-ui.production.min.js
flask_react/static/react/vendor/react-bootstrap.min.js
flask_react/static/react/vendor/react-dom.development.js
flask_react/static/react/vendor/react-dom.production.min.js
flask_react/static/react/vendor/react.development.js
flask_react/static/react/vendor/react.production.min.js
flask_react/static/react/vendor/socket.io.slim.js
flask_react/static/react/vendor/socket.io.slim.js.map
flask_react/templates/react/base.html
flask_react/templates/react/index.html