Metadata-Version: 2.1
Name: Flask-ReactJS
Version: 0.2.3
Summary: React extension for Flask
Home-page: https://github.com/gerelorant/flask_react
Author: Gere Lóránt
Author-email: gerelorant@gmail.com
License: MIT
Platform: UNKNOWN
